{
    "/js/app.js": "/js/app.js?id=af9ea419d77543188af4",
    "/css/app.css": "/css/app.css?id=967e8a3495cc771614c1",
    "/js/jquery-3.4.1.min.js": "/js/jquery-3.4.1.min.js?id=220afd743d9e9643852e",
    "/css/theme.css": "/css/theme.css?id=923122bf89d962f47e2f",
    "/js/app.min.js": "/js/app.min.js?id=af9ea419d77543188af4",
    "/css/app.min.css": "/css/app.min.css?id=967e8a3495cc771614c1",
    "/css/theme.min.css": "/css/theme.min.css?id=923122bf89d962f47e2f",
    "/css/assets/app.min.css": "/css/assets/app.min.css?id=d8d07524355c4098cb0e"
}
